geosam/__init__.py
geosam/image_encoder.py
geosam/torchgeo_sam.py
GeoSAM_Image_Encoder-1.0.4.dist-info/LICENSE
GeoSAM_Image_Encoder-1.0.4.dist-info/METADATA
GeoSAM_Image_Encoder-1.0.4.dist-info/WHEEL
GeoSAM_Image_Encoder-1.0.4.dist-info/top_level.txt
GeoSAM_Image_Encoder-1.0.4.dist-info/RECORD
