Metadata-Version: 2.1
Name: GeoSAM-Image-Encoder
Version: 1.0.4
Summary: A package for encoding satellite images into Geo-SAM features.
Home-page: https://github.com/Fanchengyan/GeoSAM-Image-Encoder
Author: Joey, Fancy
Author-email: fanchy14@lzu.edu.cn
Classifier: Programming Language :: Python :: 3
Classifier: License :: OSI Approved :: MIT License
Classifier: Operating System :: OS Independent
Requires-Python: >=3.6
License-File: LICENSE
Requires-Dist: pandas
Requires-Dist: tqdm
Requires-Dist: setuptools
Requires-Dist: torchgeo
Requires-Dist: segment-anything
